{
  "$schema": "http://json-schema.org/draft-07/schema#",
  "title": "Automation Metrics Schema",
  "type": "object",
  "additionalProperties": true,
  "properties": {
    "trace_max": {"type": ["number", "null"], "minimum": 0},
    "trace_max_sweep": {"type": ["number", "null"], "minimum": 0},
    "d2": {"type": ["number", "null"]},
  "d2_forced": {"type": ["boolean", "null"]},
    "alpha_d": {"type": ["number", "null"]},
    "fractal_transport_gap": {"type": ["number", "null"], "minimum": 0},
    "dt_order": {"type": ["number", "null"], "minimum": 0},
    "bootstrap_halfwidth": {"type": ["number", "null"], "minimum": 0},
    "cpu_time": {"type": ["number", "null"], "minimum": 0},
    "rss": {"type": ["number", "null"], "minimum": 0},
    "min_eig": {"type": ["number", "null"]},
    "neg_eig_count": {"type": ["integer", "null"], "minimum": 0},
    "adaptive_dt_rejections": {"type": ["integer", "null"], "minimum": 0},
    "adaptive_dt_mean": {"type": ["number", "null"], "minimum": 0},
    "local_error_max": {"type": ["number", "null"], "minimum": 0},
    "wall_time_seconds": {"type": ["number", "null"], "minimum": 0},
    "logical_fidelity": {"type": ["number", "null"], "minimum": 0},
  "entanglement_fidelity": {"type": ["number", "null"], "minimum": 0, "maximum": 1},
  "coherent_information": {"type": ["number", "null"]},
    "fisher_gamma": {"type": ["number", "null"], "minimum": 0},
    "fisher_gamma_sqrt": {"type": ["number", "null"], "minimum": 0},
    "phase_timings": {"type": ["object", "null"]},
    "delta_instanton": {"type": ["number", "null"]},
    "delta_instanton_S0": {"type": ["number", "null"]},
    "delta_instanton_valid": {"type": ["boolean", "null"]},
    "delta_instanton_omega0": {"type": ["number", "null"]}
    ,
    "logical_gamma_L_hz": {"type": ["number", "null"]},
    "gate_time_ns": {"type": ["number", "null"], "minimum": 0},
    "max_safe_clock_mhz": {"type": ["number", "null"], "minimum": 0},
    "ultra_qft_scaling_exponent": {"type": ["number", "null"]},
    "ultra_max_holo_violation": {"type": ["number", "null"]},
    "ultra_max_chern_number": {"type": ["number", "null"]},
    "ultra_fisher_scaling": {"type": ["number", "null"]},
    "hyper_gauge_emergence_exponent": {"type": ["number", "null"]},
    "hyper_diffeo_scaling": {"type": ["number", "null"]},
    "hyper_noncomm_theta": {"type": ["number", "null"]},
    "hyper_spectral_dimension": {"type": ["number", "null"]},
    "hyper_chaos_r_parameter": {"type": ["number", "null"]},
    "hyper_page_entropy": {"type": ["number", "null"]},
    "hyper_entropy_production_rate": {"type": ["number", "null"]},
    "hyper_auto_discoveries": {"type": ["integer", "null"], "minimum": 0},
    "hyper_auto_iterations": {"type": ["integer", "null"], "minimum": 0},
    "hyper_auto_optimal_gamma": {"type": ["number", "null"]},
    "hyper_auto_optimal_disorder": {"type": ["number", "null"]},
    "hyper_auto_efficiency": {"type": ["number", "null"]},
    "hyper_auto_anomalies_detected": {"type": ["integer", "null"], "minimum": 0},
    "hyper_auto_hypotheses_generated": {"type": ["integer", "null"], "minimum": 0},
    "hyper_auto_strategy_changes": {"type": ["integer", "null"], "minimum": 0},
    "hyper_auto_knowledge_size": {"type": ["number", "null"], "minimum": 0}
  }
}
